[{
  "id": 0,
  "first_name": "John",
  "last_name": "Smith",
  "expenses": [
    {
    "expense_id": 0,
    "category": "Equipment",
    "description": "office supplies",
    "cost": 200
    },
    {
      "expense_id": 1,
      "category": "Food",
      "description": "snacks",
      "cost": 50
    }
]
},
{
  "id": 1,
  "first_name": "Paul",
  "last_name": "Jones",
  "expenses": [
    {
    "expense_id": 0,
    "category": "Equipment",
    "description": "Toilet paper",
    "cost": 105
    },
    {
      "expense_id": 1,
      "category": "Food",
      "description": "ground meats",
      "cost": 600
    }
]
}
]
